.coveragerc
.travis.yml
AUTHORS
ChangeLog
LICENSE
MANIFEST.in
README.rst
requirements.txt
setup.cfg
setup.py
tox.ini
docs/Makefile
docs/make.bat
docs/source/conf.py
docs/source/index.rst
docs/source/readme.rst
leonardo_celery_email/__init__.py
leonardo_celery_email/backends.py
leonardo_celery_email/models.py
leonardo_celery_email/settings.py
leonardo_celery_email.egg-info/PKG-INFO
leonardo_celery_email.egg-info/SOURCES.txt
leonardo_celery_email.egg-info/dependency_links.txt
leonardo_celery_email.egg-info/not-zip-safe
leonardo_celery_email.egg-info/pbr.json
leonardo_celery_email.egg-info/requires.txt
leonardo_celery_email.egg-info/top_level.txt
leonardo_celery_email/apps/__init__.py
leonardo_celery_email/migrations/__init__.py
leonardo_celery_email/widget/__init__.py
requirements/default.txt
requirements/tests.txt
tests/cov.sh
tests/local_settings.py
tests/manage.py
tests/testapp/__init__.py
tests/testapp/models.py
tests/testapp/settings.py
tests/testapp/urls.py
tests/testapp/tests/__init__.py
tests/testapp/tests/test_commands.py